ai/__init__.py
ai/admin.py
ai/apps.py
ai/cat_cnn.py
ai/catai_cnn_new.h5
ai/forms.py
ai/models.py
ai/tests.py
ai/urls.py
ai/views.py
ai/migrations/__init__.py
ai/static/ai/cat_1.jpg
ai/static/ai/cheetah.jpg
ai/static/ai/lion.jpg
ai/static/ai/css/ai-style.css
ai/templates/ai/index.html
zfl_ai-0.0.15.dist-info/METADATA
zfl_ai-0.0.15.dist-info/WHEEL
zfl_ai-0.0.15.dist-info/licenses/LICENSE.txt
zfl_ai-0.0.15.dist-info/RECORD
