Metadata-Version: 2.1
Name: zfl-ai
Version: 0.0.15
Summary: ai on zfl
Project-URL: Documentation, https://github.com/unknown/Appのパッケージ名#readme
Project-URL: Issues, https://github.com/unknown/Appのパッケージ名/issues
Project-URL: Source, https://github.com/unknown/Appのパッケージ名
Author-email: warise <example@gmail.com>
License-Expression: MIT
License-File: LICENSE.txt
Classifier: Development Status :: 4 - Beta
Classifier: Environment :: Web Environment
Classifier: Framework :: Django
Classifier: Intended Audience :: Developers
Classifier: Programming Language :: Python
Classifier: Programming Language :: Python :: 3.6
Classifier: Programming Language :: Python :: Implementation :: CPython
Classifier: Programming Language :: Python :: Implementation :: PyPy
Requires-Python: >=3.6
Requires-Dist: django-imagekit==4.0.2
Requires-Dist: django==2.2.5
Requires-Dist: numpy==1.16.4
Requires-Dist: pillow==5.4.1
Requires-Dist: protobuf==3.20.*
Requires-Dist: tensorflow==1.15.0
